{
  "arquivo": {
    "nome": "ift cci mtf shadow 1_1.mq4",
    "tamanho_bytes": 7364,
    "linhas_codigo": 228,
    "data_modificacao": "2025-08-10T19:39:31.279395"
  },
  "analise_ftmo": {
    "score_bruto": 0.0,
    "score_final": 0.0,
    "criterios_atendidos": {},
    "penalidades_aplicadas": {},
    "riscos_detectados": [
      "ESTRATÉGIA PROIBIDA: Grid_Martingale"
    ],
    "ajustes_necessarios": [
      "INCOMPATÍVEL COM FTMO - Estratégia Grid_Martingale é proibida"
    ],
    "status_ftmo": "PROIBIDO_FTMO",
    "eliminatorio": true,
    "observacoes": [
      "EA automaticamente reprovado por usar Grid_Martingale"
    ],
    "componentes_uteis": [],
    "snippets_detectados": []
  },
  "processing_time": 0.0022666454315185547,
  "timestamp": "2025-08-13T01:12:15.554524"
}