{
  "file_info": {
    "original_name": "Givonly_SnR_SnD_modM15 [saol].mq4",
    "current_name": "IND_Givonly_SnR_SnD_modM15_saol_v1.0_FOREX.mq4",
    "current_path": "C:\\Users\\Admin\\Documents\\EA_SCALPER_XAUUSD\\CODIGO_FONTE_LIBRARY\\MQL4_Source\\Indicators\\Custom\\IND_Givonly_SnR_SnD_modM15_saol_v1.0_FOREX.mq4",
    "file_size": 10263,
    "lines_count": 258
  },
  "classification": {
    "type": "Indicator",
    "strategy": [
      "Scalping",
      "Trend_Following",
      "Volume_Analysis"
    ],
    "market_timeframe": {
      "markets": [
        "FOREX",
        "INDICES"
      ],
      "timeframes": [
        "M1",
        "M15",
        "H1",
        "H4",
        "D1"
      ],
      "confidence": 100
    },
    "ftmo_ready": false
  },
  "ftmo_analysis": {
    "ftmo_score": 0.0,
    "ftmo_level": "Não_Adequado",
    "compliance_issues": [
      "CRÍTICO: Sem Stop Loss detectado",
      "CRÍTICO: Sem gestão de risco",
      "Sem proteção de drawdown",
      "Sem limite de trades simultâneos"
    ],
    "compliance_strengths": [],
    "is_ftmo_ready": false,
    "risk_category": "High",
    "score": 0.0,
    "level": "Não_Adequado",
    "compliance_score": 0.0
  },
  "quality": {
    "score": 100,
    "complexity": 49,
    "issues": []
  },
  "code_analysis": {
    "functions": [
      "init",
      "deinit",
      "OnCalculate",
      "SND",
      "GAMBAR",
      "SNR",
      "TF",
      "HIGH",
      "LOW",
      "TULIS",
      "GARIS"
    ],
    "variables": [
      "SHOW_M15",
      "SHOW_M30",
      "SHOW_H1",
      "SHOW_H4",
      "SHOW_D1",
      "SHOW_W1",
      "Supply_Demand_Area"
    ],
    "includes": [],
    "properties": [
      "copyright",
      "link",
      "indicator_chart_window"
    ]
  },
  "tags": [
    "#Indicator",
    "#Scalping",
    "#Trend_Following",
    "#Volume_Analysis",
    "#FOREX",
    "#INDICES",
    "#M1",
    "#M15",
    "#H1",
    "#H4",
    "#D1",
    "#Nao_FTMO",
    "#HighQuality"
  ],
  "processing_info": {
    "processed_at": "2025-08-13T01:35:12.752863",
    "processor_version": "7.0",
    "analysis_complete": true
  },
  "analysis_metadata": {
    "timestamp": "2025-08-13T06:35:08.566575",
    "corrected_by": "FTMOScoreCorrector_v2.0",
    "correction_reason": "Sistema FTMO Rigoroso Ultra Crítico"
  }
}