{
  "file_info": {
    "original_name": "TDI.mq4",
    "current_name": "IND_TDI_v1.0_FOREX.mq4",
    "current_path": "C:\\Users\\Admin\\Documents\\EA_SCALPER_XAUUSD\\CODIGO_FONTE_LIBRARY\\MQL4_Source\\Indicators\\Custom\\IND_TDI_v1.0_FOREX.mq4",
    "file_size": 24691,
    "lines_count": 516
  },
  "classification": {
    "type": "Indicator",
    "strategy": [
      "Scalping",
      "SMC_ICT",
      "Trend_Following",
      "News_Trading"
    ],
    "market_timeframe": {
      "markets": [
        "FOREX",
        "GOLD",
        "INDICES"
      ],
      "timeframes": [
        "M1",
        "M5",
        "M15",
        "H1",
        "H4",
        "D1"
      ],
      "confidence": 100
    },
    "ftmo_ready": false
  },
  "ftmo_analysis": {
    "ftmo_score": 0.0,
    "ftmo_level": "Não_Adequado",
    "compliance_issues": [
      "CRÍTICO: Sem Stop Loss detectado",
      "CRÍTICO: Sem gestão de risco",
      "Sem proteção de drawdown",
      "Sem limite de trades simultâneos"
    ],
    "compliance_strengths": [],
    "is_ftmo_ready": false,
    "risk_category": "High",
    "score": 0.0,
    "level": "Não_Adequado",
    "compliance_score": 0.0
  },
  "quality": {
    "score": 88.33333333333333,
    "complexity": 61,
    "issues": []
  },
  "code_analysis": {
    "functions": [
      "init",
      "deinit",
      "start",
      "Createline",
      "CreateLabel",
      "CreateText",
      "StDev",
      "Variance",
      "TF2Str",
      "DoAlerts",
      "SignalArrowSpacer"
    ],
    "variables": [
      "NoteGeneral",
      "Show_TrendVisuals",
      "Show_SignalArrows",
      "SHIFT_Sideway",
      "SHIFT_Up_Down",
      "NoteIndic",
      "RSI_Period",
      "RSI_Price",
      "Volatility_Band",
      "RSI_Price_Line",
      "RSI_Price_Type",
      "Trade_Signal_Line",
      "SHOW_Trade_Signal_Line2",
      "Trade_Signal_Line2",
      "Trade_Signal_Type",
      "NoteAlerts",
      "BuySellAlerts",
      "CautionAlerts",
      "MsgAlerts",
      "SoundAlerts",
      "SoundAlertFile",
      "eMailAlerts"
    ],
    "includes": [],
    "properties": [
      "indicator_separate_window",
      "indicator_buffers",
      "indicator_color1",
      "indicator_color2",
      "indicator_color3",
      "indicator_width3",
      "indicator_color4",
      "indicator_color5",
      "indicator_width5",
      "indicator_color6",
      "indicator_color7",
      "indicator_style7"
    ]
  },
  "tags": [
    "#Indicator",
    "#Scalping",
    "#SMC_ICT",
    "#Trend_Following",
    "#News_Trading",
    "#FOREX",
    "#GOLD",
    "#INDICES",
    "#M1",
    "#M5",
    "#M15",
    "#H1",
    "#H4",
    "#D1",
    "#Nao_FTMO",
    "#HighQuality"
  ],
  "processing_info": {
    "processed_at": "2025-08-13T01:36:45.368148",
    "processor_version": "7.0",
    "analysis_complete": true
  },
  "analysis_metadata": {
    "timestamp": "2025-08-13T06:35:18.592547",
    "corrected_by": "FTMOScoreCorrector_v2.0",
    "correction_reason": "Sistema FTMO Rigoroso Ultra Crítico"
  }
}