{
  "file_info": {
    "original_name": "AllAbsoluteQQE_v2.3.mq4",
    "current_name": "IND_AllAbsoluteQQE_v2_3_v1.0_FOREX.mq4",
    "current_path": "C:\\Users\\Admin\\Documents\\EA_SCALPER_XAUUSD\\CODIGO_FONTE_LIBRARY\\MQL4_Source\\Indicators\\Custom\\IND_AllAbsoluteQQE_v2_3_v1.0_FOREX.mq4",
    "file_size": 48883,
    "lines_count": 1465
  },
  "classification": {
    "type": "Indicator",
    "strategy": [
      "Scalping",
      "Trend_Following",
      "Volume_Analysis"
    ],
    "market_timeframe": {
      "markets": [
        "FOREX",
        "GOLD",
        "INDICES",
        "CRYPTO"
      ],
      "timeframes": [
        "M1",
        "M5",
        "M15",
        "H1",
        "H4",
        "D1"
      ],
      "confidence": 100
    },
    "ftmo_ready": false
  },
  "ftmo_analysis": {
    "ftmo_score": 0.0,
    "ftmo_level": "Não_Adequado",
    "compliance_issues": [
      "CRÍTICO: Sem Stop Loss detectado",
      "CRÍTICO: Sem gestão de risco",
      "Sem proteção de drawdown",
      "Sem limite de trades simultâneos"
    ],
    "compliance_strengths": [],
    "is_ftmo_ready": false,
    "risk_category": "High",
    "score": 0.0,
    "level": "Não_Adequado",
    "compliance_score": 0.0
  },
  "quality": {
    "score": 91.66666666666667,
    "complexity": 241,
    "issues": []
  },
  "code_analysis": {
    "functions": [
      "init",
      "deinit",
      "start",
      "_AllAbsQQE",
      "averageName",
      "allAverages",
      "allAveragesOnArray",
      "SMA",
      "SMAOnArray",
      "EMA",
      "EMAOnArray",
      "Wilder",
      "WilderOnArray",
      "LWMA",
      "LWMAOnArray",
      "SineWMA",
      "SineWMAOnArray",
      "TriMA",
      "TriMAOnArray",
      "LSMA",
      "LSMAOnArray",
      "SMMA",
      "SMMAOnArray",
      "HMA",
      "HMAOnArray",
      "ZeroLagEMA",
      "ZeroLagEMAOnArray",
      "DEMA",
      "DEMAOnArray",
      "T3_basic",
      "T3_basicOnArray",
      "ITrend",
      "ITrendOnArray",
      "Median",
      "MedianOnArray",
      "GeoMean",
      "GeoMeanOnArray",
      "REMA",
      "REMAOnArray",
      "ILRS",
      "ILRSOnArray",
      "IE2",
      "IE2OnArray",
      "TriMA_gen",
      "TriMA_genOnArray",
      "VWMA",
      "VWMAOnArray",
      "JSmooth",
      "JSmoothOnArray",
      "SMA_eq",
      "SMA_eqOnArray",
      "ALMA",
      "ALMAOnArray",
      "TEMA",
      "TEMAOnArray",
      "T3",
      "T3OnArray",
      "Laguerre",
      "LaguerreOnArray",
      "getPivots",
      "stdDev",
      "isNewBar",
      "BoxAlert",
      "Pause",
      "WarningSound",
      "EmailAlert",
      "tf"
    ],
    "variables": [
      "TimeFrame",
      "MathMode",
      "Price",
      "Length",
      "PreSmooth",
      "Smooth",
      "MA_Method",
      "RangeAvgLength",
      "Multiplier",
      "SignalMode",
      "LevelsMode",
      "OverboughtLevel",
      "OversoldLevel",
      "LookBackPeriod",
      "UpperMultiplier",
      "LowerMultiplier",
      "alerts",
      "AlertMode",
      "SoundsNumber",
      "SoundsPause",
      "UpSound",
      "DnSound",
      "EmailMode",
      "EmailsNumber",
      "i"
    ],
    "includes": [],
    "properties": [
      "copyright",
      "link",
      "indicator_separate_window",
      "indicator_buffers",
      "indicator_color1",
      "indicator_color2",
      "indicator_color3",
      "indicator_color4",
      "indicator_color5",
      "indicator_color6",
      "indicator_color7",
      "indicator_width1",
      "indicator_width2",
      "indicator_width3",
      "indicator_width4",
      "indicator_width5",
      "indicator_style6",
      "indicator_style7",
      "indicator_level1",
      "indicator_levelcolor"
    ]
  },
  "tags": [
    "#Indicator",
    "#Scalping",
    "#Trend_Following",
    "#Volume_Analysis",
    "#FOREX",
    "#GOLD",
    "#INDICES",
    "#CRYPTO",
    "#M1",
    "#M5",
    "#M15",
    "#H1",
    "#H4",
    "#D1",
    "#Nao_FTMO",
    "#HighQuality"
  ],
  "processing_info": {
    "processed_at": "2025-08-13T01:30:56.842662",
    "processor_version": "7.0",
    "analysis_complete": true
  },
  "analysis_metadata": {
    "timestamp": "2025-08-13T06:35:01.307540",
    "corrected_by": "FTMOScoreCorrector_v2.0",
    "correction_reason": "Sistema FTMO Rigoroso Ultra Crítico"
  }
}