{
  "file_info": {
    "original_name": "XAUUSD_ATR_TrendGrid.mq4",
    "current_name": "EA_XAUUSD_ATR_TrendGrid_v1.0_FOREX.mq4",
    "current_path": "C:\\Users\\Admin\\Documents\\EA_SCALPER_XAUUSD\\CODIGO_FONTE_LIBRARY\\MQL4_Source\\EAs\\Scalping\\EA_XAUUSD_ATR_TrendGrid_v1.0_FOREX.mq4",
    "file_size": 7257,
    "lines_count": 171
  },
  "classification": {
    "type": "EA",
    "strategy": [
      "Scalping",
      "Grid_Martingale",
      "SMC_ICT",
      "Trend_Following",
      "News_Trading"
    ],
    "market_timeframe": {
      "markets": [
        "FOREX",
        "GOLD"
      ],
      "timeframes": [
        "M1",
        "M15",
        "H1",
        "H4"
      ],
      "confidence": 100
    },
    "ftmo_ready": false
  },
  "ftmo_analysis": {
    "ftmo_score": 0.0,
    "ftmo_level": "Não_Adequado",
    "compliance_issues": [
      "CRÍTICO: Sem Stop Loss detectado",
      "CRÍTICO: Sem gestão de risco",
      "Sem proteção de drawdown",
      "CRÍTICO: Estratégia de alto risco (Grid/Martingale)",
      "Sem limite de trades simultâneos"
    ],
    "compliance_strengths": [
      "Filtros de sessão"
    ],
    "is_ftmo_ready": false,
    "risk_category": "High",
    "score": 0.0,
    "level": "Não_Adequado",
    "compliance_score": 0.0
  },
  "quality": {
    "score": 100,
    "complexity": 30,
    "issues": []
  },
  "code_analysis": {
    "functions": [
      "GetRealSMA",
      "GetSMAAngle",
      "GetATR",
      "LowerOpenBuyPrice",
      "HasOpenBuyTrades",
      "PlaceBuyGrid",
      "ManageTrailingStops",
      "OnInit",
      "OnDeinit",
      "OnTick"
    ],
    "variables": [
      "ATR_Multiplier",
      "Grid_Orders",
      "RSI_Buy_Level",
      "Trail_ATR_Multiplier",
      "SMA_Angle_Min",
      "ATR_Period",
      "LotSize",
      "MagicNumber",
      "Slippage",
      "SlopeBarsBack",
      "SMA_Bars"
    ],
    "includes": [],
    "properties": [
      "strict"
    ]
  },
  "tags": [
    "#EA",
    "#Scalping",
    "#Grid_Martingale",
    "#SMC_ICT",
    "#Trend_Following",
    "#News_Trading",
    "#FOREX",
    "#GOLD",
    "#M1",
    "#M15",
    "#H1",
    "#H4",
    "#Nao_FTMO",
    "#HighQuality"
  ],
  "processing_info": {
    "processed_at": "2025-08-13T01:37:07.991305",
    "processor_version": "7.0",
    "analysis_complete": true
  },
  "analysis_metadata": {
    "timestamp": "2025-08-13T06:34:59.813339",
    "corrected_by": "FTMOScoreCorrector_v2.0",
    "correction_reason": "Sistema FTMO Rigoroso Ultra Crítico"
  }
}